COPYING
ChangeLog
MANIFEST.in
README.txt
omp-cli.rst
setup.cfg
setup.py
doc/omp-cli.1
doc/omp-cli.html
openvas/__init__.py
openvas.omplib.egg-info/PKG-INFO
openvas.omplib.egg-info/SOURCES.txt
openvas.omplib.egg-info/dependency_links.txt
openvas.omplib.egg-info/entry_points.txt
openvas.omplib.egg-info/namespace_packages.txt
openvas.omplib.egg-info/requires.txt
openvas.omplib.egg-info/top_level.txt
openvas.omplib.egg-info/zip-safe
openvas/omplib/__init__.py
openvas/omplib/cmd.py
openvas/omplib/xmlpp.py
tests/new_task_empty_rc.xml
tests/test_omplib.py