Metadata-Version: 1.0
Name: openvas.omplib
Version: 0.0.1dev-r7741
Summary: An OMP (OpenVAS Management Protocol) client interface for Python
Home-page: http://www.openvas.org/
Author: Hartmut Goebel
Author-email: h.goebel@goebel-consult.de
License: GPL 3.0
Keywords: OpenVAS,OMP,OpenVAS Management Protocol,Nessus
Platform: UNKNOWN
Classifier: Development Status :: 4 - Beta
Classifier: Environment :: Console
Classifier: Intended Audience :: Developers
Classifier: Intended Audience :: Information Technology
Classifier: Intended Audience :: System Administrators
Classifier: License :: OSI Approved :: GNU General Public License (GPL)
Classifier: Natural Language :: English
Classifier: Operating System :: OS Independent
Classifier: Programming Language :: Python
Classifier: Programming Language :: Python :: 2.5
Classifier: Programming Language :: Python :: 2.6
Classifier: Programming Language :: Python :: 2.7
Classifier: Topic :: Security
Classifier: Topic :: Software Development :: Libraries :: Python Modules
